stopover/__init__.py
stopover/errors.py
stopover/stopover.py
stopover/utils.py
stopover-1.2301.0.dist-info/METADATA
stopover-1.2301.0.dist-info/WHEEL
stopover-1.2301.0.dist-info/top_level.txt
stopover-1.2301.0.dist-info/RECORD
