Metadata-Version: 2.1
Name: stopover
Version: 1.2301.0
Summary: Stopover's Python SDK
Home-page: 
Author: Rodrigo Martínez Castaño
Author-email: rodrigo@martinez.gal
License: GNU General Public License v3 (GPLv3)
Classifier: Development Status :: 4 - Beta
Classifier: Environment :: Console
Classifier: Intended Audience :: Developers
Classifier: License :: OSI Approved :: GNU General Public License v3 (GPLv3)
Classifier: Operating System :: POSIX :: Linux
Classifier: Programming Language :: Python :: 3.6
Classifier: Programming Language :: Python :: Implementation :: PyPy
Classifier: Topic :: Software Development :: Libraries :: Python Modules
Requires-Python: >=3.6
Requires-Dist: msgpack (<2.0.0,>=1.0.2)
Requires-Dist: python-snappy (<1.0.0,>=0.5.4)
Requires-Dist: requests (<3.0.0,>=2.24.0)
